torchaudio/__init__.py
torchaudio/_torchcodec.py
torchaudio/version.py
torchaudio/.dylibs/libc++.1.0.dylib
torchaudio/_extension/__init__.py
torchaudio/_extension/utils.py
torchaudio/_internal/__init__.py
torchaudio/_internal/module_utils.py
torchaudio/compliance/__init__.py
torchaudio/compliance/kaldi.py
torchaudio/datasets/__init__.py
torchaudio/datasets/cmuarctic.py
torchaudio/datasets/cmudict.py
torchaudio/datasets/commonvoice.py
torchaudio/datasets/dr_vctk.py
torchaudio/datasets/fluentcommands.py
torchaudio/datasets/gtzan.py
torchaudio/datasets/iemocap.py
torchaudio/datasets/librilight_limited.py
torchaudio/datasets/librimix.py
torchaudio/datasets/librispeech.py
torchaudio/datasets/librispeech_biasing.py
torchaudio/datasets/libritts.py
torchaudio/datasets/ljspeech.py
torchaudio/datasets/musdb_hq.py
torchaudio/datasets/quesst14.py
torchaudio/datasets/snips.py
torchaudio/datasets/speechcommands.py
torchaudio/datasets/tedlium.py
torchaudio/datasets/utils.py
torchaudio/datasets/vctk.py
torchaudio/datasets/voxceleb1.py
torchaudio/datasets/yesno.py
torchaudio/functional/__init__.py
torchaudio/functional/_alignment.py
torchaudio/functional/filtering.py
torchaudio/functional/functional.py
torchaudio/lib/__init__.py
torchaudio/lib/_torchaudio.so
torchaudio/lib/libtorchaudio.so
torchaudio/models/__init__.py
torchaudio/models/_hdemucs.py
torchaudio/models/conformer.py
torchaudio/models/conv_tasnet.py
torchaudio/models/deepspeech.py
torchaudio/models/emformer.py
torchaudio/models/rnnt.py
torchaudio/models/rnnt_decoder.py
torchaudio/models/tacotron2.py
torchaudio/models/wav2letter.py
torchaudio/models/wavernn.py
torchaudio/models/decoder/__init__.py
torchaudio/models/decoder/_ctc_decoder.py
torchaudio/models/decoder/_cuda_ctc_decoder.py
torchaudio/models/squim/__init__.py
torchaudio/models/squim/objective.py
torchaudio/models/squim/subjective.py
torchaudio/models/wav2vec2/__init__.py
torchaudio-2.10.0.dist-info/METADATA
torchaudio-2.10.0.dist-info/WHEEL
torchaudio-2.10.0.dist-info/top_level.txt
torchaudio-2.10.0.dist-info/RECORD
torchaudio-2.10.0.dist-info/licenses/LICENSE
